fhir_kindling/__init__.py
fhir_kindling/fhir_query/__init__.py
fhir_kindling/fhir_query/fhir_query.py
fhir_kindling/fhir_query/query_parameters.py
fhir_kindling/fhir_query/query_response.py
fhir_kindling/fhir_server/__init__.py
fhir_kindling/fhir_server/auth.py
fhir_kindling/fhir_server/fhir_server.py
fhir_kindling/fhir_server/server_responses.py
fhir_kindling/figures/__init__.py
fhir_kindling/figures/resource_plots.py
fhir_kindling/figures/summary.py
fhir_kindling/generators/__init__.py
fhir_kindling/generators/dataset.py
fhir_kindling/generators/field_generator.py
fhir_kindling/generators/names.py
fhir_kindling/generators/patient.py
fhir_kindling/generators/resource_generator.py
fhir_kindling/serde/__init__.py
fhir_kindling/serde/flatten.py
fhir_kindling/util/__init__.py
fhir_kindling/util/references.py
fhir_kindling/util/resources.py
fhir_kindling-0.9.0.dist-info/LICENSE
fhir_kindling-0.9.0.dist-info/METADATA
fhir_kindling-0.9.0.dist-info/WHEEL
fhir_kindling-0.9.0.dist-info/entry_points.txt
fhir_kindling-0.9.0.dist-info/top_level.txt
fhir_kindling-0.9.0.dist-info/RECORD
