Metadata-Version: 2.1
Name: fhir-kindling
Version: 0.9.0
Summary: CRUD Operations against FHIR servers, resource validation and synthetic FHIR resource generation.
Home-page: https://github.com/migraf/fhir-kindling
Author: Michael Graf
Author-email: michael.graf@uni-tuebingen.de
License: MIT license
Keywords: fhir_kindling,fhir,pydantic,health,data,hl7
Classifier: Development Status :: 4 - Beta
Classifier: Intended Audience :: Developers
Classifier: License :: OSI Approved :: MIT License
Classifier: Natural Language :: English
Classifier: Programming Language :: Python :: 3
Classifier: Programming Language :: Python :: 3.7
Classifier: Programming Language :: Python :: 3.8
Classifier: Programming Language :: Python :: 3.9
Requires-Python: >=3.7
License-File: LICENSE
Requires-Dist: python-dotenv
Requires-Dist: fhir.resources
Requires-Dist: httpx
Requires-Dist: pandas
Requires-Dist: authlib
Requires-Dist: pendulum
Requires-Dist: orjson
Requires-Dist: xmltodict
Requires-Dist: pydantic
Requires-Dist: networkx
Provides-Extra: csv
Requires-Dist: pandas ; extra == 'csv'
